ask_the_wizard/__init__.py
ask_the_wizard/pip_importer.py
ask_the_wizard/wizard_communication.py
ask_the_wizard/wizard_executer.py
ask_the_wizard/wizard_importer.py
ask_the_wizard-0.0.1rc1.dist-info/LICENSE
ask_the_wizard-0.0.1rc1.dist-info/METADATA
ask_the_wizard-0.0.1rc1.dist-info/WHEEL
ask_the_wizard-0.0.1rc1.dist-info/top_level.txt
ask_the_wizard-0.0.1rc1.dist-info/RECORD
