Metadata-Version: 2.1
Name: ask-the-wizard
Version: 0.0.1rc1
Summary: Are you still thinking while coding or are you already Asking The Wizard? 🧙
Home-page: https://github.com/tizianerlenberg/ask_the_wizard
Author: Andreas Menzel, Tizian Erlenberg
Author-email: mail@andreas-menzel.com
License: MIT
Classifier: License :: OSI Approved :: MIT License
Classifier: Programming Language :: Python :: 3.10
Classifier: Operating System :: OS Independent
Requires-Python: >=3.10
License-File: LICENSE
Requires-Dist: python-dotenv ~=1.0.0
Requires-Dist: openai ~=1.6.1
Requires-Dist: requests ~=2.31.0
Provides-Extra: dev
Requires-Dist: pytest >=7.0 ; extra == 'dev'
Requires-Dist: twine >=4.0.2 ; extra == 'dev'
